enocean2mqtt/__init__.py
enocean2mqtt/communicator.py
enocean2mqtt/conf.py
enocean2mqtt/device.py
enocean2mqtt/schema.py
enocean2mqtt/strings.py
enocean2mqtt/utils.py
enocean2mqtt-0.2.1.dist-info/LICENSE
enocean2mqtt-0.2.1.dist-info/METADATA
enocean2mqtt-0.2.1.dist-info/WHEEL
enocean2mqtt-0.2.1.dist-info/entry_points.txt
enocean2mqtt-0.2.1.dist-info/top_level.txt
enocean2mqtt-0.2.1.dist-info/RECORD
