Metadata-Version: 2.1
Name: enocean2mqtt
Version: 0.2.1
Summary: EnOcean to MQTT bridge
Home-page: https://github.com/matthieuvw/enocean2mqtt
Author: Matthieu Van Wynsberghe
Author-email: matthieu.vw@disroot.org
License: UNKNOWN
Keywords: enocean,mqtt
Platform: UNKNOWN
Classifier: Development Status :: 4 - Beta
Classifier: Programming Language :: Python :: 3
Classifier: Operating System :: OS Independent
Classifier: License :: OSI Approved :: GNU General Public License v3 (GPLv3)
Requires-Python: >=3.7
Requires-Dist: jsonschema (==3.2.0)
Requires-Dist: enocean (==0.60.0)
Requires-Dist: pyyaml (==5.4.1)
Requires-Dist: paho-mqtt (==1.5.1)
